runplify/__init__.py
runplify/_version.py
runplify/handlers.py
runplify-0.2.0.data/data/share/jupyter/labextensions/runplify/package.json
runplify-0.2.0.data/data/share/jupyter/labextensions/runplify/static/568.e38683257ebdb098c0c6.js
runplify-0.2.0.data/data/share/jupyter/labextensions/runplify/static/747.60ed6a99ed82bdaa9fc3.js
runplify-0.2.0.data/data/share/jupyter/labextensions/runplify/static/remoteEntry.8dd3e6868ae901451388.js
runplify-0.2.0.data/data/share/jupyter/labextensions/runplify/static/style.js
runplify-0.2.0.data/data/share/jupyter/labextensions/runplify/static/third-party-licenses.json
runplify-0.2.0.data/data/share/jupyter/labextensions/runplify/install.json
runplify-0.2.0.dist-info/METADATA
runplify-0.2.0.dist-info/WHEEL
runplify-0.2.0.dist-info/licenses/LICENSE
runplify-0.2.0.dist-info/RECORD
